README.md
setup.py
pytoolz/__init__.py
pytoolz.egg-info/PKG-INFO
pytoolz.egg-info/SOURCES.txt
pytoolz.egg-info/dependency_links.txt
pytoolz.egg-info/top_level.txt
pytoolz/cache/__init__.py
pytoolz/cache/memoize.py
pytoolz/design/__init__.py
pytoolz/design/observer.py
pytoolz/design/singleton.py
pytoolz/design/traits.py
pytoolz/ds/__init__.py
pytoolz/ds/linkedlist.py
pytoolz/functional/__init__.py
pytoolz/functional/iterables.py
pytoolz/functional/pipe.py
pytoolz/log/__init__.py
pytoolz/log/logger.py
pytoolz/log/logperf.py
pytoolz/multiprocessing/__init__.py
pytoolz/multiprocessing/pool.py
pytoolz/multiprocessing/processify.py
pytoolz/serialization/__init__.py
pytoolz/serialization/serializers.py