Metadata-Version: 1.1
Name: pytoolz
Version: 0.1.7
Summary: UNKNOWN
Home-page: https://github.com/andrea-lascola/Pytoolz
Author: Andrea La Scola
Author-email: andrealascola@gmail.com
License: Creative Commons Attribution-Noncommercial-Share Alike license
Platform: UNKNOWN
Classifier: License :: OSI Approved :: MIT License
Classifier: Programming Language :: Python
Classifier: Programming Language :: Python :: 3
Classifier: Programming Language :: Python :: 3.7
Classifier: Programming Language :: Python :: Implementation :: CPython
Classifier: Programming Language :: Python :: Implementation :: PyPy
